mcp_fs/__init__.py
mcp_fs/backend_manager.py
mcp_fs/cli.py
mcp_fs/dal.py
mcp_fs/mcp_server.py
mcp_fs-0.1.8.dist-info/WHEEL
mcp_fs-0.1.8.dist-info/entry_points.txt
mcp_fs-0.1.8.dist-info/METADATA
mcp_fs-0.1.8.dist-info/RECORD
