Metadata-Version: 2.3
Name: mcp-fs
Version: 0.1.8
Summary: MCP-FS is an MCP server that supports managing multiple types of file systems, such as local FS, S3, R2, B2, WebDAV, and others, in one MCP server. It is built on top of OpenDAL.
Keywords: mcp,filesystem,opendal,s3,webdav
Author: Vaayne
Author-email: Vaayne <liu.vaayne@gmail.com>
License: MIT
Classifier: Development Status :: 4 - Beta
Classifier: Intended Audience :: Developers
Classifier: License :: OSI Approved :: MIT License
Classifier: Operating System :: OS Independent
Classifier: Programming Language :: Python :: 3
Classifier: Programming Language :: Python :: 3.11
Classifier: Programming Language :: Python :: 3.12
Classifier: Programming Language :: Python :: 3.13
Classifier: Topic :: System :: Filesystems
Classifier: Topic :: Software Development :: Libraries :: Python Modules
Requires-Dist: fastmcp>=2.13.0
Requires-Dist: opendal>=0.45.20
Requires-Dist: uvicorn>=0.35.0
Requires-Dist: click>=8.1.0
Requires-Python: >=3.12
Project-URL: Homepage, https://github.com/vaayne/cc-plugins
Project-URL: Issues, https://github.com/vaayne/cc-plugins/issues
Project-URL: Repository, https://github.com/vaayne/cc-plugins
